[
  {
    "name": "Process Start",
    "start": 1611582819486,
    "end": 1611582820295,
    "duration": 809,
    "pid": 16472,
    "index": 0
  },
  {
    "name": "Application Start",
    "start": 1611582820296,
    "end": 1611582821098,
    "duration": 802,
    "pid": 16472,
    "index": 1
  },
  {
    "name": "Load Plugin",
    "start": 1611582820303,
    "end": 1611582820327,
    "duration": 24,
    "pid": 16472,
    "index": 2
  },
  {
    "name": "Load Config",
    "start": 1611582820328,
    "end": 1611582820364,
    "duration": 36,
    "pid": 16472,
    "index": 3
  },
  {
    "name": "Require(0) config/config.default.js",
    "start": 1611582820329,
    "end": 1611582820329,
    "duration": 0,
    "pid": 16472,
    "index": 4
  },
  {
    "name": "Require(1) node_modules/egg-session/config/config.default.js",
    "start": 1611582820331,
    "end": 1611582820332,
    "duration": 1,
    "pid": 16472,
    "index": 5
  },
  {
    "name": "Require(2) node_modules/egg-security/config/config.default.js",
    "start": 1611582820332,
    "end": 1611582820333,
    "duration": 1,
    "pid": 16472,
    "index": 6
  },
  {
    "name": "Require(3) node_modules/egg-jsonp/config/config.default.js",
    "start": 1611582820335,
    "end": 1611582820336,
    "duration": 1,
    "pid": 16472,
    "index": 7
  },
  {
    "name": "Require(4) node_modules/egg-onerror/config/config.default.js",
    "start": 1611582820337,
    "end": 1611582820338,
    "duration": 1,
    "pid": 16472,
    "index": 8
  },
  {
    "name": "Require(5) node_modules/egg-i18n/config/config.default.js",
    "start": 1611582820338,
    "end": 1611582820339,
    "duration": 1,
    "pid": 16472,
    "index": 9
  },
  {
    "name": "Require(6) node_modules/egg-watcher/config/config.default.js",
    "start": 1611582820340,
    "end": 1611582820341,
    "duration": 1,
    "pid": 16472,
    "index": 10
  },
  {
    "name": "Require(7) node_modules/egg-schedule/config/config.default.js",
    "start": 1611582820342,
    "end": 1611582820343,
    "duration": 1,
    "pid": 16472,
    "index": 11
  },
  {
    "name": "Require(8) node_modules/egg-multipart/config/config.default.js",
    "start": 1611582820344,
    "end": 1611582820344,
    "duration": 0,
    "pid": 16472,
    "index": 12
  },
  {
    "name": "Require(9) node_modules/egg-development/config/config.default.js",
    "start": 1611582820345,
    "end": 1611582820346,
    "duration": 1,
    "pid": 16472,
    "index": 13
  },
  {
    "name": "Require(10) node_modules/egg-logrotator/config/config.default.js",
    "start": 1611582820346,
    "end": 1611582820347,
    "duration": 1,
    "pid": 16472,
    "index": 14
  },
  {
    "name": "Require(11) node_modules/egg-static/config/config.default.js",
    "start": 1611582820348,
    "end": 1611582820348,
    "duration": 0,
    "pid": 16472,
    "index": 15
  },
  {
    "name": "Require(12) node_modules/egg-view/config/config.default.js",
    "start": 1611582820349,
    "end": 1611582820350,
    "duration": 1,
    "pid": 16472,
    "index": 16
  },
  {
    "name": "Require(13) node_modules/egg-mysql/config/config.default.js",
    "start": 1611582820351,
    "end": 1611582820352,
    "duration": 1,
    "pid": 16472,
    "index": 17
  },
  {
    "name": "Require(14) node_modules/egg-cors/config/config.default.js",
    "start": 1611582820353,
    "end": 1611582820354,
    "duration": 1,
    "pid": 16472,
    "index": 18
  },
  {
    "name": "Require(15) node_modules/egg/config/config.default.js",
    "start": 1611582820354,
    "end": 1611582820355,
    "duration": 1,
    "pid": 16472,
    "index": 19
  },
  {
    "name": "Require(16) config/config.default.js",
    "start": 1611582820357,
    "end": 1611582820357,
    "duration": 0,
    "pid": 16472,
    "index": 20
  },
  {
    "name": "Require(17) node_modules/egg-security/config/config.local.js",
    "start": 1611582820359,
    "end": 1611582820359,
    "duration": 0,
    "pid": 16472,
    "index": 21
  },
  {
    "name": "Require(18) node_modules/egg-watcher/config/config.local.js",
    "start": 1611582820360,
    "end": 1611582820361,
    "duration": 1,
    "pid": 16472,
    "index": 22
  },
  {
    "name": "Require(19) node_modules/egg-view/config/config.local.js",
    "start": 1611582820362,
    "end": 1611582820363,
    "duration": 1,
    "pid": 16472,
    "index": 23
  },
  {
    "name": "Require(20) node_modules/egg/config/config.local.js",
    "start": 1611582820363,
    "end": 1611582820364,
    "duration": 1,
    "pid": 16472,
    "index": 24
  },
  {
    "name": "Load extend/application.js",
    "start": 1611582820365,
    "end": 1611582820381,
    "duration": 16,
    "pid": 16472,
    "index": 25
  },
  {
    "name": "Require(21) node_modules/egg-session/app/extend/application.js",
    "start": 1611582820366,
    "end": 1611582820368,
    "duration": 2,
    "pid": 16472,
    "index": 26
  },
  {
    "name": "Require(22) node_modules/egg-security/app/extend/application.js",
    "start": 1611582820368,
    "end": 1611582820370,
    "duration": 2,
    "pid": 16472,
    "index": 27
  },
  {
    "name": "Require(23) node_modules/egg-jsonp/app/extend/application.js",
    "start": 1611582820371,
    "end": 1611582820373,
    "duration": 2,
    "pid": 16472,
    "index": 28
  },
  {
    "name": "Require(24) node_modules/egg-logrotator/app/extend/application.js",
    "start": 1611582820374,
    "end": 1611582820376,
    "duration": 2,
    "pid": 16472,
    "index": 29
  },
  {
    "name": "Require(25) node_modules/egg-view/app/extend/application.js",
    "start": 1611582820377,
    "end": 1611582820378,
    "duration": 1,
    "pid": 16472,
    "index": 30
  },
  {
    "name": "Load extend/request.js",
    "start": 1611582820381,
    "end": 1611582820391,
    "duration": 10,
    "pid": 16472,
    "index": 31
  },
  {
    "name": "Require(26) node_modules/egg/app/extend/request.js",
    "start": 1611582820385,
    "end": 1611582820386,
    "duration": 1,
    "pid": 16472,
    "index": 32
  },
  {
    "name": "Load extend/response.js",
    "start": 1611582820391,
    "end": 1611582820398,
    "duration": 7,
    "pid": 16472,
    "index": 33
  },
  {
    "name": "Require(27) node_modules/egg/app/extend/response.js",
    "start": 1611582820393,
    "end": 1611582820395,
    "duration": 2,
    "pid": 16472,
    "index": 34
  },
  {
    "name": "Load extend/context.js",
    "start": 1611582820398,
    "end": 1611582820505,
    "duration": 107,
    "pid": 16472,
    "index": 35
  },
  {
    "name": "Require(28) node_modules/egg-security/app/extend/context.js",
    "start": 1611582820399,
    "end": 1611582820427,
    "duration": 28,
    "pid": 16472,
    "index": 36
  },
  {
    "name": "Require(29) node_modules/egg-jsonp/app/extend/context.js",
    "start": 1611582820428,
    "end": 1611582820429,
    "duration": 1,
    "pid": 16472,
    "index": 37
  },
  {
    "name": "Require(30) node_modules/egg-i18n/app/extend/context.js",
    "start": 1611582820430,
    "end": 1611582820431,
    "duration": 1,
    "pid": 16472,
    "index": 38
  },
  {
    "name": "Require(31) node_modules/egg-multipart/app/extend/context.js",
    "start": 1611582820432,
    "end": 1611582820496,
    "duration": 64,
    "pid": 16472,
    "index": 39
  },
  {
    "name": "Require(32) node_modules/egg-view/app/extend/context.js",
    "start": 1611582820497,
    "end": 1611582820498,
    "duration": 1,
    "pid": 16472,
    "index": 40
  },
  {
    "name": "Require(33) node_modules/egg/app/extend/context.js",
    "start": 1611582820498,
    "end": 1611582820500,
    "duration": 2,
    "pid": 16472,
    "index": 41
  },
  {
    "name": "Load extend/helper.js",
    "start": 1611582820506,
    "end": 1611582820533,
    "duration": 27,
    "pid": 16472,
    "index": 42
  },
  {
    "name": "Require(34) node_modules/egg-security/app/extend/helper.js",
    "start": 1611582820506,
    "end": 1611582820527,
    "duration": 21,
    "pid": 16472,
    "index": 43
  },
  {
    "name": "Require(35) node_modules/egg/app/extend/helper.js",
    "start": 1611582820530,
    "end": 1611582820530,
    "duration": 0,
    "pid": 16472,
    "index": 44
  },
  {
    "name": "Load app.js",
    "start": 1611582820533,
    "end": 1611582820625,
    "duration": 92,
    "pid": 16472,
    "index": 45
  },
  {
    "name": "Require(36) node_modules/egg-session/app.js",
    "start": 1611582820534,
    "end": 1611582820536,
    "duration": 2,
    "pid": 16472,
    "index": 46
  },
  {
    "name": "Require(37) node_modules/egg-security/app.js",
    "start": 1611582820536,
    "end": 1611582820538,
    "duration": 2,
    "pid": 16472,
    "index": 47
  },
  {
    "name": "Require(38) node_modules/egg-onerror/app.js",
    "start": 1611582820539,
    "end": 1611582820547,
    "duration": 8,
    "pid": 16472,
    "index": 48
  },
  {
    "name": "Require(39) node_modules/egg-i18n/app.js",
    "start": 1611582820547,
    "end": 1611582820568,
    "duration": 21,
    "pid": 16472,
    "index": 49
  },
  {
    "name": "Require(40) node_modules/egg-watcher/app.js",
    "start": 1611582820569,
    "end": 1611582820573,
    "duration": 4,
    "pid": 16472,
    "index": 50
  },
  {
    "name": "Require(41) node_modules/egg-schedule/app.js",
    "start": 1611582820574,
    "end": 1611582820575,
    "duration": 1,
    "pid": 16472,
    "index": 51
  },
  {
    "name": "Require(42) node_modules/egg-multipart/app.js",
    "start": 1611582820575,
    "end": 1611582820576,
    "duration": 1,
    "pid": 16472,
    "index": 52
  },
  {
    "name": "Require(43) node_modules/egg-development/app.js",
    "start": 1611582820576,
    "end": 1611582820577,
    "duration": 1,
    "pid": 16472,
    "index": 53
  },
  {
    "name": "Require(44) node_modules/egg-logrotator/app.js",
    "start": 1611582820577,
    "end": 1611582820577,
    "duration": 0,
    "pid": 16472,
    "index": 54
  },
  {
    "name": "Require(45) node_modules/egg-static/app.js",
    "start": 1611582820578,
    "end": 1611582820578,
    "duration": 0,
    "pid": 16472,
    "index": 55
  },
  {
    "name": "Require(46) node_modules/egg-mysql/app.js",
    "start": 1611582820579,
    "end": 1611582820621,
    "duration": 42,
    "pid": 16472,
    "index": 56
  },
  {
    "name": "Require(47) node_modules/egg-cors/app.js",
    "start": 1611582820622,
    "end": 1611582820622,
    "duration": 0,
    "pid": 16472,
    "index": 57
  },
  {
    "name": "Before Start in node_modules/egg-watcher/lib/init.js:15:14",
    "start": 1611582820648,
    "end": 1611582821095,
    "duration": 447,
    "pid": 16472,
    "index": 58
  },
  {
    "name": "Before Start in node_modules/egg-mysql/lib/mysql.js:20:7",
    "start": 1611582820804,
    "end": 1611582821097,
    "duration": 293,
    "pid": 16472,
    "index": 59
  },
  {
    "name": "Load Service",
    "start": 1611582820805,
    "end": 1611582820820,
    "duration": 15,
    "pid": 16472,
    "index": 60
  },
  {
    "name": "Load \"service\" to Context",
    "start": 1611582820805,
    "end": 1611582820820,
    "duration": 15,
    "pid": 16472,
    "index": 61
  },
  {
    "name": "Load Middleware",
    "start": 1611582820820,
    "end": 1611582821058,
    "duration": 238,
    "pid": 16472,
    "index": 62
  },
  {
    "name": "Load \"middlewares\" to Application",
    "start": 1611582820820,
    "end": 1611582821038,
    "duration": 218,
    "pid": 16472,
    "index": 63
  },
  {
    "name": "Load Controller",
    "start": 1611582821058,
    "end": 1611582821062,
    "duration": 4,
    "pid": 16472,
    "index": 64
  },
  {
    "name": "Load \"controller\" to Application",
    "start": 1611582821058,
    "end": 1611582821062,
    "duration": 4,
    "pid": 16472,
    "index": 65
  },
  {
    "name": "Load Router",
    "start": 1611582821062,
    "end": 1611582821068,
    "duration": 6,
    "pid": 16472,
    "index": 66
  },
  {
    "name": "Require(48) app/router.js",
    "start": 1611582821062,
    "end": 1611582821063,
    "duration": 1,
    "pid": 16472,
    "index": 67
  },
  {
    "name": "Before Start in node_modules/egg-core/lib/egg.js:303:10",
    "start": 1611582821064,
    "end": 1611582821081,
    "duration": 17,
    "pid": 16472,
    "index": 68
  }
]